[{"year":"1980","humanCapital":"0.70","physicalCapital":"3.63","labor":"0.95","tfp":"0.53","realGdpGrowth":"5.81"},{"year":"1981","humanCapital":"0.71","physicalCapital":"3.01","labor":"1.42","tfp":"-4.46","realGdpGrowth":"0.68"},{"year":"1982","humanCapital":"0.21","physicalCapital":"1.85","labor":"1.51","tfp":"-4.50","realGdpGrowth":"-0.93"},{"year":"1983","humanCapital":"0.75","physicalCapital":"0.69","labor":"0.75","tfp":"-4.66","realGdpGrowth":"-2.47"},{"year":"1984","humanCapital":"0.76","physicalCapital":"0.92","labor":"1.76","tfp":"0.26","realGdpGrowth":"3.70"},{"year":"1985","humanCapital":"0.57","physicalCapital":"2.28","labor":"2.19","tfp":"-2.20","realGdpGrowth":"2.84"},{"year":"1986","humanCapital":"0.73","physicalCapital":"1.56","labor":"1.70","tfp":"-0.20","realGdpGrowth":"3.79"},{"year":"1987","humanCapital":"0.57","physicalCapital":"1.57","labor":"1.56","tfp":"-0.58","realGdpGrowth":"3.12"},{"year":"1988","humanCapital":"0.74","physicalCapital":"1.54","labor":"1.35","tfp":"-2.72","realGdpGrowth":"0.91"},{"year":"1989","humanCapital":"0.47","physicalCapital":"1.30","labor":"0.98","tfp":"-1.46","realGdpGrowth":"1.29"},{"year":"1990","humanCapital":"0.41","physicalCapital":"1.16","labor":"1.20","tfp":"-2.25","realGdpGrowth":"0.52"},{"year":"1991","humanCapital":"0.04","physicalCapital":"2.17","labor":"1.17","tfp":"0.52","realGdpGrowth":"3.90"},{"year":"1992","humanCapital":"0.09","physicalCapital":"1.67","labor":"1.20","tfp":"0.37","realGdpGrowth":"3.33"},{"year":"1993","humanCapital":"0.47","physicalCapital":"1.90","labor":"1.11","tfp":"0.52","realGdpGrowth":"4.00"},{"year":"1994","humanCapital":"0.57","physicalCapital":"2.11","labor":"1.26","tfp":"0.91","realGdpGrowth":"4.85"},{"year":"1995","humanCapital":"0.54","physicalCapital":"1.44","labor":"-0.08","tfp":"-1.22","realGdpGrowth":"0.68"},{"year":"1996","humanCapital":"0.51","physicalCapital":"1.63","labor":"0.94","tfp":"0.58","realGdpGrowth":"3.66"},{"year":"1997","humanCapital":"0.61","physicalCapital":"2.27","labor":"1.48","tfp":"0.97","realGdpGrowth":"5.33"},{"year":"1998","humanCapital":"0.35","physicalCapital":"2.32","labor":"1.09","tfp":"-1.28","realGdpGrowth":"2.48"},{"year":"1999","humanCapital":"0.18","physicalCapital":"1.64","labor":"0.61","tfp":"-2.48","realGdpGrowth":"-0.05"},{"year":"2000","humanCapital":"0.51","physicalCapital":"1.87","labor":"1.17","tfp":"-0.10","realGdpGrowth":"3.45"},{"year":"2001","humanCapital":"0.73","physicalCapital":"1.52","labor":"0.51","tfp":"-2.26","realGdpGrowth":"0.50"},{"year":"2002","humanCapital":"0.53","physicalCapital":"1.14","labor":"0.00","tfp":"-1.76","realGdpGrowth":"-0.09"},{"year":"2003","humanCapital":"0.64","physicalCapital":"1.08","labor":"0.96","tfp":"-0.70","realGdpGrowth":"1.98"},{"year":"2004","humanCapital":"0.39","physicalCapital":"1.43","labor":"1.58","tfp":"2.47","realGdpGrowth":"5.87"},{"year":"2005","humanCapital":"0.16","physicalCapital":"1.84","labor":"0.92","tfp":"1.44","realGdpGrowth":"4.36"},{"year":"2006","humanCapital":"0.26","physicalCapital":"2.21","labor":"1.10","tfp":"1.76","realGdpGrowth":"5.33"},{"year":"2007","humanCapital":"0.49","physicalCapital":"2.68","labor":"0.85","tfp":"1.38","realGdpGrowth":"5.40"},{"year":"2008","humanCapital":"0.53","physicalCapital":"2.91","labor":"1.03","tfp":"-0.71","realGdpGrowth":"3.76"},{"year":"2009","humanCapital":"0.44","physicalCapital":"1.96","labor":"0.25","tfp":"-4.80","realGdpGrowth":"-2.15"},{"year":"2010","humanCapital":"0.49","physicalCapital":"2.42","labor":"0.90","tfp":"2.19","realGdpGrowth":"6.00"},{"year":"2011","humanCapital":"0.44","physicalCapital":"2.60","labor":"0.89","tfp":"0.55","realGdpGrowth":"4.48"},{"year":"2012","humanCapital":"0.74","physicalCapital":"2.30","labor":"0.71","tfp":"-1.00","realGdpGrowth":"2.75"},{"year":"2013","humanCapital":"0.48","physicalCapital":"2.09","labor":"0.75","tfp":"-0.47","realGdpGrowth":"2.85"},{"year":"2014","humanCapital":"0.51","physicalCapital":"1.75","labor":"0.35","tfp":"-1.40","realGdpGrowth":"1.21"},{"year":"2015","humanCapital":"0.21","physicalCapital":"1.35","labor":"0.30","tfp":"-1.64","realGdpGrowth":"0.22"},{"year":"2016","humanCapital":"0.47","physicalCapital":"0.97","labor":"-0.35","tfp":"-2.13","realGdpGrowth":"-1.04"},{"year":"2017","humanCapital":"0.28","physicalCapital":"1.00","labor":"0.44","tfp":"-0.54","realGdpGrowth":"1.18"},{"year":"2018","humanCapital":"0.55","physicalCapital":"1.04","labor":"0.76","tfp":"-1.40","realGdpGrowth":"0.95"},{"year":"2019","humanCapital":"0.40","physicalCapital":"0.93","labor":"0.75","tfp":"-2.22","realGdpGrowth":"-0.14"},{"year":"2020","humanCapital":"1.25","physicalCapital":"0.48","labor":"-7.62","tfp":"-1.30","realGdpGrowth":"-7.19"},{"year":"2021","humanCapital":"0.00","physicalCapital":"1.06","labor":"6.48","tfp":"-0.95","realGdpGrowth":"6.59"},{"year":"2022","humanCapital":"0.23","physicalCapital":"1.17","labor":"3.00","tfp":"-0.78","realGdpGrowth":"3.62"},{"year":"2023","humanCapital":"0.22","physicalCapital":"1.06","labor":"-0.02","tfp":"-0.38","realGdpGrowth":"0.88"}]